[
     {
        "from": "威廉（狗腿子上司）",
        "to": ["Ignacio", "1037315288"],
        "title": "紧急案件指派 - 优先级1A：儿童绑架案（UNC-451）",
        "body": "你已被指派为本案的首席调查员之一。你的首要任务是与当地警方成立的联合任务组（JTTF）协同工作，并由露西·贝茨探员总体协调。案件性质为儿童绑架。受害者：吉娜·贝尔福，5岁，白人女性，患有严重慢性病，需持续用药维持生命。离了药，她活不过几天。嫌疑人： 至少两名。主嫌之一，乔治·刘易斯顿，前ATF探员，在商场内制造混乱后，于我们的人抵达时当众自杀。其同伙，一名身份不明的女性，带走了受害者。"
    }，

      {
        "from": "威廉（狗腿子上司）",
        "to": ["Ignacio", "1037315288"],
        "title": "案件 UNC-451（儿童绑架案） - 非传统威胁分析支持资源",
        "body": "你们关于受害者父母所属团体——即“逾越天使教会”——的信仰体系可能与此案动机存在潜在关联的初步评估，已被采纳。鉴于该团体已知的极端意识形态，本案已被认定存在潜在的、非传统威胁维度，为了确保调查视角的全面性，并协助解读可能遇到的非常规符号体系或行为模式，我已通过总部协调，为你争取到专项顾问支持。"
     }，
]
